systran_align.cpython-36m-x86_64-linux-gnu.so
systran_align.libs/libfastalign-04ac3fa0.so
systran_align.libs/libgomp-a34b3233.so.1.0.0
systran_align-3.5.0.dist-info/RECORD
systran_align-3.5.0.dist-info/top_level.txt
systran_align-3.5.0.dist-info/WHEEL
systran_align-3.5.0.dist-info/METADATA
