Metadata-Version: 2.1
Name: systran-align
Version: 3.5.0
Summary: Alignment tool based on fast_align
Home-page: UNKNOWN
Author: SYSTRAN
Author-email: guillaume.klein@systrangroup.com
License: UNKNOWN
Platform: UNKNOWN
Classifier: Development Status :: 4 - Beta
Classifier: Intended Audience :: Developers
Classifier: Intended Audience :: Science/Research
Classifier: Programming Language :: Python
Classifier: Topic :: Text Processing :: Linguistic
Classifier: Topic :: Software Development :: Libraries :: Python Modules
